[{"x":"127","y":"134","t":[16,28,47,73,80,102,148],"v":["THEFT F/AUTO","MOTOR VEHICLE THEFT","BURGLARY","ROBBERY","THEFT F/AUTO","BURGLARY","ROBBERY"]},{"x":"238","y":"190","t":[17,19,28,46,57,90,91,70,82,109,139,139],"v":["THEFT F/AUTO","THEFT F/AUTO","ASSAULT W/DANGEROUS WEAPON","THEFT/OTHER","ROBBERY","THEFT F/AUTO","THEFT F/AUTO","THEFT/OTHER","THEFT/OTHER","THEFT/OTHER","THEFT/OTHER","THEFT/OTHER"]},{"x":"14","y":"74","t":[11,21,0,114,139],"v":["THEFT F/AUTO","ASSAULT W/DANGEROUS WEAPON","ROBBERY","ROBBERY","THEFT F/AUTO"]},{"x":"104","y":"253","t":[11,14,3,0,7,48,48,57,85,122],"v":["BURGLARY","THEFT F/AUTO","THEFT F/AUTO","THEFT F/AUTO","THEFT F/AUTO","THEFT F/AUTO","THEFT F/AUTO","THEFT/OTHER","ASSAULT W/DANGEROUS WEAPON","ASSAULT W/DANGEROUS WEAPON"]},{"x":"21","y":"145","t":[11,15,84,113],"v":["THEFT F/AUTO","THEFT F/AUTO","BURGLARY","THEFT/OTHER"]},{"x":"104","y":"39","t":[59,89],"v":["THEFT F/AUTO","THEFT/OTHER"]}]