[{"x":"169","y":"73","t":[19],"v":["THEFT/OTHER"]},{"x":"66","y":"98","t":[19,38,38,48,77],"v":["THEFT F/AUTO","THEFT F/AUTO","THEFT F/AUTO","BURGLARY","THEFT F/AUTO"]},{"x":"120","y":"116","t":[12],"v":["ASSAULT W/DANGEROUS WEAPON"]},{"x":"193","y":"162","t":[27,35,37,55,117],"v":["THEFT/OTHER","THEFT F/AUTO","THEFT/OTHER","THEFT/OTHER","BURGLARY"]},{"x":"152","y":"20","t":[33],"v":["THEFT F/AUTO"]},{"x":"21","y":"54","t":[53],"v":["THEFT/OTHER"]},{"x":"140","y":"232","t":[54,138],"v":["THEFT F/AUTO","ROBBERY"]},{"x":"21","y":"232","t":[62,118],"v":["THEFT F/AUTO","THEFT/OTHER"]},{"x":"115","y":"54","t":[92],"v":["THEFT F/AUTO"]},{"x":"66","y":"0","t":[82,99,120,142],"v":["THEFT F/AUTO","THEFT F/AUTO","THEFT F/AUTO","THEFT F/AUTO"]}]