[{"x":"33","y":"238","t":[30,142],"v":["THEFT/OTHER","ROBBERY"]},{"x":"253","y":"86","t":[57,116],"v":["THEFT/OTHER","BURGLARY"]},{"x":"196","y":"12","t":[51,73],"v":["THEFT F/AUTO","THEFT/OTHER"]},{"x":"33","y":"12","t":[106],"v":["ASSAULT W/DANGEROUS WEAPON"]},{"x":"33","y":"158","t":[99,118,110,134],"v":["THEFT/OTHER","THEFT F/AUTO","THEFT F/AUTO","THEFT F/AUTO"]},{"x":"140","y":"198","t":[127],"v":["MOTOR VEHICLE THEFT"]},{"x":"140","y":"122","t":[132],"v":["THEFT F/AUTO"]},{"x":"33","y":"86","t":[133],"v":["THEFT F/AUTO"]}]