[{"x":"49","y":"78","t":[10],"v":["BURGLARY"]},{"x":"55","y":"245","t":[46],"v":["THEFT/OTHER"]},{"x":"125","y":"244","t":[40],"v":["THEFT F/AUTO"]},{"x":"52","y":"187","t":[59],"v":["THEFT F/AUTO"]},{"x":"202","y":"127","t":[94],"v":["THEFT F/AUTO"]},{"x":"81","y":"43","t":[92],"v":["THEFT/OTHER"]},{"x":"243","y":"99","t":[77],"v":["THEFT F/AUTO"]},{"x":"119","y":"76","t":[124,144],"v":["THEFT F/AUTO","THEFT/OTHER"]},{"x":"160","y":"156","t":[117],"v":["MOTOR VEHICLE THEFT"]},{"x":"203","y":"182","t":[136],"v":["THEFT F/AUTO"]}]