[{"x":"42","y":"18","t":[17,0,0,4,42,96,74,64,85,121,134],"v":["THEFT/OTHER","THEFT F/AUTO","THEFT/OTHER","THEFT F/AUTO","THEFT F/AUTO","THEFT/OTHER","THEFT/OTHER","THEFT F/AUTO","THEFT/OTHER","THEFT F/AUTO","THEFT F/AUTO"]},{"x":"16","y":"158","t":[11,31,126,132],"v":["THEFT F/AUTO","THEFT F/AUTO","ROBBERY","ROBBERY"]},{"x":"76","y":"131","t":[13,90,106],"v":["THEFT/OTHER","THEFT F/AUTO","THEFT F/AUTO"]},{"x":"88","y":"246","t":[14,39,106,108,139,145],"v":["THEFT/OTHER","ROBBERY","THEFT F/AUTO","THEFT/OTHER","THEFT F/AUTO","THEFT/OTHER"]},{"x":"105","y":"88","t":[27,10,108],"v":["THEFT/OTHER","THEFT/OTHER","THEFT/OTHER"]},{"x":"187","y":"149","t":[33,37],"v":["BURGLARY","THEFT F/AUTO"]},{"x":"254","y":"15","t":[45,125],"v":["ASSAULT W/DANGEROUS WEAPON","ROBBERY"]},{"x":"71","y":"71","t":[38,86,102,124,141],"v":["THEFT F/AUTO","THEFT F/AUTO","THEFT F/AUTO","THEFT F/AUTO","MOTOR VEHICLE THEFT"]},{"x":"128","y":"214","t":[38],"v":["THEFT F/AUTO"]},{"x":"118","y":"50","t":[48],"v":["MOTOR VEHICLE THEFT"]},{"x":"42","y":"115","t":[55,124,129,130],"v":["MOTOR VEHICLE THEFT","THEFT F/AUTO","THEFT/OTHER","THEFT/OTHER"]},{"x":"124","y":"111","t":[68],"v":["THEFT/OTHER"]},{"x":"43","y":"165","t":[66],"v":["THEFT/OTHER"]},{"x":"254","y":"112","t":[76,103],"v":["MOTOR VEHICLE THEFT","THEFT F/AUTO"]},{"x":"83","y":"184","t":[81,103],"v":["MOTOR VEHICLE THEFT","THEFT F/AUTO"]},{"x":"99","y":"5","t":[103,142,148],"v":["THEFT F/AUTO","THEFT F/AUTO","THEFT F/AUTO"]},{"x":"152","y":"3","t":[127,111,146,142,129],"v":["THEFT F/AUTO","THEFT F/AUTO","THEFT F/AUTO","THEFT/OTHER","BURGLARY"]},{"x":"247","y":"53","t":[121],"v":["ROBBERY"]},{"x":"157","y":"82","t":[121],"v":["THEFT F/AUTO"]},{"x":"15","y":"96","t":[122],"v":["THEFT F/AUTO"]},{"x":"43","y":"215","t":[123,145,132],"v":["THEFT F/AUTO","THEFT F/AUTO","THEFT F/AUTO"]},{"x":"100","y":"58","t":[145],"v":["THEFT F/AUTO"]},{"x":"157","y":"58","t":[143,140],"v":["THEFT/OTHER","THEFT F/AUTO"]},{"x":"159","y":"95","t":[138],"v":["THEFT/OTHER"]},{"x":"166","y":"241","t":[132],"v":["THEFT F/AUTO"]}]